python_todo_comments/__init__.py
python_todo_comments/main.py
python_todo_comments-0.3.0.dist-info/entry_points.txt
python_todo_comments-0.3.0.dist-info/WHEEL
python_todo_comments-0.3.0.dist-info/METADATA
python_todo_comments-0.3.0.dist-info/RECORD
